spaceone/__init__.py
spaceone/tester/__init__.py
spaceone/tester/unittest.py
spaceone/tester/conf/__init__.py
spaceone/tester/conf/global_conf.py
spaceone/tester/scenario/__init__.py
spaceone/tester/scenario/scenario.py
spaceone/tester/scenario/runner/__init__.py
spaceone/tester/scenario/runner/runner.py
spaceone/tester/scenario/runner/identity/__init__.py
spaceone/tester/scenario/runner/identity/api_key_runner.py
spaceone/tester/scenario/runner/identity/domain_runner.py
spaceone/tester/scenario/runner/identity/project_runner.py
spaceone/tester/scenario/runner/identity/role_binding_runner.py
spaceone/tester/scenario/runner/identity/role_runner.py
spaceone/tester/scenario/runner/identity/service_account_runner.py
spaceone/tester/scenario/runner/identity/user_runner.py
spaceone/tester/scenario/runner/inventory/__init__.py
spaceone/tester/scenario/runner/inventory/collector_runner.py
spaceone/tester/scenario/runner/inventory/region_zone_pool_runner.py
spaceone/tester/scenario/runner/inventory/resource_group_runner.py
spaceone/tester/scenario/runner/monitoring/__init__.py
spaceone/tester/scenario/runner/monitoring/datasource_runner.py
spaceone/tester/scenario/runner/power_scheduler/__init__.py
spaceone/tester/scenario/runner/power_scheduler/schedule_runner.py
spaceone/tester/scenario/runner/repository/__init__.py
spaceone/tester/scenario/runner/repository/repository_runner.py
spaceone/tester/scenario/runner/secret/__init__.py
spaceone/tester/scenario/runner/secret/secret_group_runner.py
spaceone/tester/scenario/runner/secret/secret_runner.py
spaceone/tester/scenario/runner/statistics/__init__.py
spaceone/tester/scenario/runner/statistics/schedule_runner.py
cloudforet_tester-1.1.1.dist-info/METADATA
cloudforet_tester-1.1.1.dist-info/WHEEL
cloudforet_tester-1.1.1.dist-info/top_level.txt
cloudforet_tester-1.1.1.dist-info/RECORD
