Metadata-Version: 2.1
Name: cloudforet-tester
Version: 1.1.1
Summary: SpaceONE test framework
Home-page: https://www.spaceone.dev/
Author: MEGAZONE SpaceONE Team
Author-email: admin@spaceone.dev
License: Apache License 2.0
Platform: UNKNOWN
Requires-Dist: spaceone-core
Requires-Dist: spaceone-api
Requires-Dist: python-consul
